owl/__init__.py
owl/abi_fetcher.py
owl/config.py
owl/contract.py
owl/exceptions.py
owl/utils.py
owl_contracts-0.1.7.dist-info/METADATA
owl_contracts-0.1.7.dist-info/WHEEL
owl_contracts-0.1.7.dist-info/top_level.txt
owl_contracts-0.1.7.dist-info/RECORD
