Metadata-Version: 2.4
Name: owl-contracts
Version: 0.1.7
Summary: A Python library to retrieve smart contract function metadata and data from EVM-compatible blockchains
Author: Saurabh Kumar
License: MIT
Project-URL: Homepage, https://github.com/yourusername/owl
Project-URL: Documentation, https://github.com/yourusername/owl#readme
Project-URL: Repository, https://github.com/yourusername/owl
Keywords: ethereum,smart-contracts,web3,blockchain,abi
Classifier: Development Status :: 3 - Alpha
Classifier: Intended Audience :: Developers
Classifier: License :: OSI Approved :: MIT License
Classifier: Programming Language :: Python :: 3
Classifier: Programming Language :: Python :: 3.8
Classifier: Programming Language :: Python :: 3.9
Classifier: Programming Language :: Python :: 3.10
Classifier: Programming Language :: Python :: 3.11
Classifier: Programming Language :: Python :: 3.12
Classifier: Topic :: Software Development :: Libraries :: Python Modules
Requires-Python: >=3.8
Requires-Dist: web3>=6.0.0
Requires-Dist: requests>=2.28.0
Provides-Extra: dev
Requires-Dist: pytest>=7.0.0; extra == "dev"
Requires-Dist: pytest-mock>=3.10.0; extra == "dev"
